Hermetica-1.0.0.dist-info/METADATA
Hermetica-1.0.0.dist-info/RECORD
Hermetica-1.0.0.dist-info/WHEEL
Hermetica-1.0.0.dist-info/entry_points.txt
Hermetica-1.0.0.dist-info/top_level.txt
hermetica/__init__.py
hermetica/cli.py
hermetica/scaffold/__init__.py
hermetica/scaffold/api.py
hermetica/scaffold/app.py
hermetica/scaffold/config.py
hermetica/scaffold/decorator.py
hermetica/scaffold/docker.py
hermetica/scaffold/extension.py
hermetica/scaffold/model.py
hermetica/scaffold/pipfile.py
hermetica/scaffold/test.py
hermetica/scaffold/wsgi.py
